pdf_play/__init__.py
pdf_play/__main__.py
pdf_play/__settings__.py
pdf_play/core/__init__.py
pdf_play/core/__settings__.py
pdf_play/core/_pdf.py
pdf_play/core/_watermark.py
pdf_play/helpers/__init__.py
pdf_play/helpers/_input_actions.py
pdf_play/helpers/_input_types.py
pdf_play/helpers/_parser.py
pdf_play/helpers/_utils.py
pdf_play-1.2.6.dist-info/LICENSE
pdf_play-1.2.6.dist-info/METADATA
pdf_play-1.2.6.dist-info/WHEEL
pdf_play-1.2.6.dist-info/entry_points.txt
pdf_play-1.2.6.dist-info/top_level.txt
pdf_play-1.2.6.dist-info/RECORD
